{
    "author_name": {
        "name": "Naftali Kaminski",
        "clusters_count": 1
    },
    "author_data": {
        "A5088823841": {
            "gold_id/master_key": "Naftali_Kaminski_1",
            "ids": [
                "A5088823841",
                "A5125661478",
                "A5129032979",
                "A5123606646",
                "A5126725635",
                "A5123765301",
                "A5123985256",
                "A5126233974"
            ],
            "name": "Naftali Kaminski",
            "name_first": "Naftali",
            "name_middle": "",
            "name_last": "Kaminski",
            "field": null,
            "fields": null,
            "email": null,
            "linkedin": null,
            "socials": [],
            "works_count": 872,
            "works": [
                "W3011134208",
                "W1998975199",
                "W2019926860",
                "W2150103989",
                "W2440054067",
                "W3041062936",
                "W2157869208",
                "W2204697639",
                "W2159864284",
                "W2055245602",
                "W3016965350",
                "W4379879135",
                "W4387012832",
                "W1990584310",
                "W2037645843",
                "W2160639837",
                "W2009001235",
                "W2137064182",
                "W1662007645",
                "W2136761840",
                "W1980798450",
                "W2031123734",
                "W3165670466",
                "W2038482344",
                "W2007414618",
                "W2112871329",
                "W1979141644",
                "W2892890999",
                "W2772430771",
                "W2160906692",
                "W1987104810",
                "W1976639712",
                "W2122387572",
                "W2983449145",
                "W2053375738",
                "W2034338127",
                "W4211067148",
                "W2135454149",
                "W2147346503",
                "W2041143782",
                "W2124952231",
                "W1970379805",
                "W2107272258",
                "W2940024093",
                "W2028008068",
                "W3154836057",
                "W2742995736",
                "W2929609469",
                "W2163128715",
                "W2689866037",
                "W2993523018",
                "W2045959886",
                "W2120169383",
                "W1979937536",
                "W2122958293",
                "W2087442158",
                "W4210263666",
                "W3089952857",
                "W1976574577",
                "W2918255006",
                "W2128361433",
                "W2098148891",
                "W2041217784",
                "W1979209470",
                "W2121709368",
                "W2784709509",
                "W2161650328",
                "W2142374046",
                "W2059379939",
                "W2756020545",
                "W4207060592",
                "W2129873144",
                "W2979790944",
                "W2087125765",
                "W2036939554",
                "W2745223933",
                "W2152007940",
                "W2054352916",
                "W3004379083",
                "W1537253598",
                "W2580916015",
                "W2168911526",
                "W1988013567",
                "W4226055473",
                "W2793938361",
                "W3025346321",
                "W2132302757",
                "W2153787061",
                "W2591274003",
                "W4297221499",
                "W2069032581",
                "W2163675951",
                "W2112613073",
                "W2533435663",
                "W4221038504",
                "W2530653220",
                "W2079355678",
                "W3033400552",
                "W2059121736",
                "W2871400816",
                "W7128624208",
                "W7128637092",
                "W7135197411",
                "W7125577882",
                "W7125787044",
                "W7129574810"
            ]
        }
    }
}